[
  {
    "id": "1",
    "title": "Transcription",
    "description": "Convert spoken content from saved audio or YouTube videos into accurate, downloadable text.",
    "image": "/featured/transcribe.png",
    "url": "/services/transcribe"
  },
  {
    "id": "2",
    "title": "Summary",
    "description": "Generate concise and detailed summaries from your transcriptions to enhance learning and retention.",
    "image": "/featured/summarize.png",
    "url": "/services/summarize"
  },
  {
    "id": "3",
    "title": "Flashcard",
    "description": "Turn key concepts from transcriptions into interactive flashcards to reinforce knowledge.",
    "image": "/featured/audio.png",
    "url": "/services/flashcards"
  },
  {
    "id": "4",
    "title": "Quiz",
    "description": "Test your understanding with multiple-choice and written-response quizzes based on your transcripts.",
    "image": "/featured/video.png",
    "url": "/services/quizzes"
  }
]
